[
  {
    "id": "b7ed7785-a797-4153-8d9b-1887f1891e25",
    "data": [
      {
        "text": "We are going to get to the bottom of this so that you can eat as normally as possible.",
        "userDefined": false
      }
    ],
    "isTemplate": false,
    "count": 0,
    "lang": "en",
    "updated": 0
  },
  {
    "id": "67d7945c-67e5-48a4-a9ba-e2056b0f7e39",
    "data": [
      {
        "text": "I cannot tell you this at the time, until I find out more information, but I can tell you I will do everything in my power to return you to a normal diet.",
        "userDefined": false
      }
    ],
    "isTemplate": false,
    "count": 0,
    "lang": "en",
    "updated": 0
  },
  {
    "id": "76b7e2a8-2ce7-4d77-a7dc-2a9bb95ab4c2",
    "data": [
      {
        "text": "I am going to perform a barium swallow study with you to assess your swallowing.",
        "userDefined": false
      }
    ],
    "isTemplate": false,
    "count": 0,
    "lang": "en",
    "updated": 0
  },
  {
    "id": "6319ad15-cbec-497a-a44d-4a8ec44babff",
    "data": [
      {
        "text": "Then we will talk about ways to possibly strengthen your swallowing and possibly get you to a more normal diet.",
        "userDefined": false
      }
    ],
    "isTemplate": false,
    "count": 0,
    "lang": "en",
    "updated": 0
  },
  {
    "id": "d5a41a7b-9f5b-42a6-91a7-a8d934bbee53",
    "data": [
      {
        "text": "Ok, we\u0027ll do a barium swallow study on you and see where exactly it is that you\u0027re having difficulty swallowing.",
        "userDefined": false
      }
    ],
    "isTemplate": false,
    "count": 0,
    "lang": "en",
    "updated": 0
  },
  {
    "id": "e256a427-368d-432f-b63c-3ff9d72dd689",
    "data": [
      {
        "text": "yes- we take an xray of your swallow so we can see what\u0027s going on more clearly",
        "userDefined": false
      }
    ],
    "isTemplate": false,
    "count": 0,
    "lang": "en",
    "updated": 0
  },
  {
    "id": "2ec7316b-3431-415f-bd53-0c5f7bfbf1a1",
    "data": [
      {
        "text": "we are going to do the best we can to get your life as close to normal as possible",
        "userDefined": false
      }
    ],
    "isTemplate": false,
    "count": 0,
    "lang": "en",
    "updated": 0
  },
  {
    "id": "25001b13-71d8-4811-b10d-b7f46f5f1255",
    "data": [
      {
        "text": "we\u0027re going to do the best we can to get your life as close to normal as possible",
        "userDefined": false
      }
    ],
    "isTemplate": false,
    "count": 0,
    "lang": "en",
    "updated": 0
  },
  {
    "id": "3a61abe4-beba-4bcb-b3ae-1f4b921a65f3",
    "data": [
      {
        "text": "Well, I don\u0027t intend to sound like a slave driver.",
        "userDefined": false
      }
    ],
    "isTemplate": false,
    "count": 0,
    "lang": "en",
    "updated": 0
  },
  {
    "id": "5ba7b38b-fda2-4347-a14a-63e754b3bb19",
    "data": [
      {
        "text": "I would like to help you",
        "userDefined": false
      }
    ],
    "isTemplate": false,
    "count": 0,
    "lang": "en",
    "updated": 0
  },
  {
    "id": "03ca92b4-8771-4618-98fe-785aebd14d89",
    "data": [
      {
        "text": "I\u0027m not sure Vinny. But we might be able to try some therapy to help you.",
        "userDefined": false
      }
    ],
    "isTemplate": false,
    "count": 0,
    "lang": "en",
    "updated": 0
  },
  {
    "id": "5f69ecc8-9045-4bd1-b849-d03cd2df8258",
    "data": [
      {
        "text": "We are going to try to get you back to eating normal foods.",
        "userDefined": false
      }
    ],
    "isTemplate": false,
    "count": 0,
    "lang": "en",
    "updated": 0
  },
  {
    "id": "8879e839-03e2-46d2-b865-c52d3ed8f5ad",
    "data": [
      {
        "text": "I look forward to working with you/",
        "userDefined": false
      }
    ],
    "isTemplate": false,
    "count": 0,
    "lang": "en",
    "updated": 0
  },
  {
    "id": "938b754e-4a2a-42c4-9159-cbe83d8b0ec9",
    "data": [
      {
        "text": "Hi Vinny. I don\u0027t know if you will be able to eat like before but let\u0027s take a look and try to figure it out.",
        "userDefined": false
      }
    ],
    "isTemplate": false,
    "count": 0,
    "lang": "en",
    "updated": 0
  },
  {
    "id": "3676615e-8ae4-4529-a559-0f2e8de9f4ac",
    "data": [
      {
        "text": "I will do my best",
        "userDefined": false
      }
    ],
    "isTemplate": false,
    "count": 0,
    "lang": "en",
    "updated": 0
  },
  {
    "id": "86956328-b90f-40b3-8159-2c71fc27a129",
    "data": [
      {
        "text": "We will see what we can do Vinny.",
        "userDefined": false
      }
    ],
    "isTemplate": false,
    "count": 0,
    "lang": "en",
    "updated": 0
  },
  {
    "id": "40dbdada-c4e8-478a-8403-897bc8146a97",
    "data": [
      {
        "text": "Okay then. I think that\u0027s all. Thank you for your time.",
        "userDefined": false
      }
    ],
    "isTemplate": false,
    "count": 0,
    "lang": "en",
    "updated": 0
  },
  {
    "id": "29ea587b-dcf4-460b-a844-924cac0c1708",
    "data": [
      {
        "text": "Well, we\u0027ll do our best to help you be comfortable.",
        "userDefined": false
      }
    ],
    "isTemplate": false,
    "count": 0,
    "lang": "en",
    "updated": 0
  },
  {
    "id": "8a78f244-5641-41a5-b892-57c92ae7bb6e",
    "data": [
      {
        "text": "I\u0027m going to ask you some more questions and do some tests.  Then I will let you know if this is possible.",
        "userDefined": false
      }
    ],
    "isTemplate": false,
    "count": 0,
    "lang": "en",
    "updated": 0
  },
  {
    "id": "e9b3c83b-e2ff-408b-b6c4-401ab43d3a41",
    "data": [
      {
        "text": "I am going to recommend some new exercises",
        "userDefined": false
      }
    ],
    "isTemplate": false,
    "count": 0,
    "lang": "en",
    "updated": 0
  },
  {
    "id": "1ab35e7f-298a-4d71-9406-ed9b831e4cef",
    "data": [
      {
        "text": "I understand.",
        "userDefined": false
      }
    ],
    "isTemplate": false,
    "count": 0,
    "lang": "en",
    "updated": 0
  },
  {
    "id": "653243ec-28c9-4231-9365-3dda1c327394",
    "data": [
      {
        "text": "okay thats all the questions i have, thanks!",
        "userDefined": false
      }
    ],
    "isTemplate": false,
    "count": 0,
    "lang": "en",
    "updated": 0
  },
  {
    "id": "32eb9710-e47d-4fdb-a69e-61c0c3bca15a",
    "data": [
      {
        "text": "See you later",
        "userDefined": false
      }
    ],
    "isTemplate": false,
    "count": 0,
    "lang": "en",
    "updated": 0
  },
  {
    "id": "fb9c0d59-08ce-4e0f-a43b-ed0cdff65755",
    "data": [
      {
        "text": "I understand your worries",
        "userDefined": false
      }
    ],
    "isTemplate": false,
    "count": 0,
    "lang": "en",
    "updated": 0
  },
  {
    "id": "c538b8bf-2891-4e87-8d98-5d0b19a0c9b8",
    "data": [
      {
        "text": "Hang in there!  I will be sure to help you get the necessary therapy you need to improve your swallowing and get you back to a normal diet.",
        "userDefined": false
      }
    ],
    "isTemplate": false,
    "count": 0,
    "lang": "en",
    "updated": 0
  },
  {
    "id": "ad6b0022-dccd-49b4-9d46-5570f7fdd20a",
    "data": [
      {
        "text": "Okay, Vinny thank you for your time",
        "userDefined": false
      }
    ],
    "isTemplate": false,
    "count": 0,
    "lang": "en",
    "updated": 0
  },
  {
    "id": "77741524-d342-444a-bc13-c194f1cb4d6e",
    "data": [
      {
        "text": "Thank you for your time Vinny",
        "userDefined": false
      }
    ],
    "isTemplate": false,
    "count": 0,
    "lang": "en",
    "updated": 0
  },
  {
    "id": "dd4fc8cc-bf92-4076-b647-570907c34511",
    "data": [
      {
        "text": "I can\u0027t make any guarantees, but after doing an assessment I can recommend some therapy techniques that can potentially improve your swallowing.",
        "userDefined": false
      }
    ],
    "isTemplate": false,
    "count": 0,
    "lang": "en",
    "updated": 0
  },
  {
    "id": "dd855183-4b8a-468f-b9e4-3771c40d4083",
    "data": [
      {
        "text": "thank you for your time",
        "userDefined": false
      }
    ],
    "isTemplate": false,
    "count": 0,
    "lang": "en",
    "updated": 0
  },
  {
    "id": "b1a76571-f4c4-4019-ab5f-518da7e71a01",
    "data": [
      {
        "text": "ok we will look into it",
        "userDefined": false
      }
    ],
    "isTemplate": false,
    "count": 0,
    "lang": "en",
    "updated": 0
  },
  {
    "id": "57440471-e2b0-400d-83ee-c912309c9a78",
    "data": [
      {
        "text": "Congratulations",
        "userDefined": false
      }
    ],
    "isTemplate": false,
    "count": 0,
    "lang": "en",
    "updated": 0
  },
  {
    "id": "00176794-cf2d-43a5-8d64-90823fd10504",
    "data": [
      {
        "text": "That is good.",
        "userDefined": false
      }
    ],
    "isTemplate": false,
    "count": 0,
    "lang": "en",
    "updated": 0
  },
  {
    "id": "d4d5fbd3-666f-49ae-92ac-e21437407dda",
    "data": [
      {
        "text": "have a nice day",
        "userDefined": false
      }
    ],
    "isTemplate": false,
    "count": 0,
    "lang": "en",
    "updated": 0
  },
  {
    "id": "1061d3fa-fb5c-47ef-9bbf-5b7fa4175970",
    "data": [
      {
        "text": "Have a wonderful day",
        "userDefined": false
      }
    ],
    "isTemplate": false,
    "count": 0,
    "lang": "en",
    "updated": 0
  },
  {
    "id": "4a12791d-5ff1-4927-b4dd-62e0c16aa427",
    "data": [
      {
        "text": "keep enjoying life",
        "userDefined": false
      }
    ],
    "isTemplate": false,
    "count": 0,
    "lang": "en",
    "updated": 0
  },
  {
    "id": "4abd28f1-5fcc-48a7-acc6-fc4ddb364227",
    "data": [
      {
        "text": "Thanks for coming ",
        "userDefined": false
      },
      {
        "text": "today",
        "meta": "@sys.ignore",
        "userDefined": false
      },
      {
        "text": ".",
        "userDefined": false
      }
    ],
    "isTemplate": false,
    "count": 0,
    "lang": "en",
    "updated": 0
  },
  {
    "id": "8ba5e86d-024d-4b68-86cc-129d0fba4bcd",
    "data": [
      {
        "text": "I will try to help.",
        "userDefined": false
      }
    ],
    "isTemplate": false,
    "count": 0,
    "lang": "en",
    "updated": 0
  }
]